cdk_datadog_integration/__init__.py
cdk_datadog_integration/py.typed
cdk_datadog_integration/_jsii/__init__.py
cdk_datadog_integration/_jsii/cdk-datadog-integration@2.1.5.jsii.tgz
cdk_datadog_integration-2.1.5.dist-info/LICENSE
cdk_datadog_integration-2.1.5.dist-info/METADATA
cdk_datadog_integration-2.1.5.dist-info/WHEEL
cdk_datadog_integration-2.1.5.dist-info/top_level.txt
cdk_datadog_integration-2.1.5.dist-info/RECORD
